yctest1/__init__.py
yctest1/cli/__init__.py
yctest1/cli/init.py
yctest1/cli/main.py
yctest1/cli/reset.py
yctest1/config.yaml
yctest1-0.1.1.dist-info/METADATA
yctest1-0.1.1.dist-info/WHEEL
yctest1-0.1.1.dist-info/entry_points.txt
yctest1-0.1.1.dist-info/RECORD
