Metadata-Version: 2.1
Name: yctest1
Version: 0.1.1
Summary: 
Author: Yunchang
Author-email: youyc88@outlook.com
Requires-Python: >=3.10,<3.13
Classifier: Programming Language :: Python :: 3
Classifier: Programming Language :: Python :: 3.10
Classifier: Programming Language :: Python :: 3.11
Classifier: Programming Language :: Python :: 3.12
Requires-Dist: ylz-utils (>=0.1.11,<0.2.0)
